{"index.md":"IoeEMIuF","ing.md":"DTrBR9yg","readme.md":"D5n-KkNJ","src_guide_getting-started.md":"ChtL3Mtx","src_guide_why.md":"DZl37MYP","src_questions_artificial-intelligence_1_基础理论.md":"Ba3sY47u","src_questions_artificial-intelligence_2_基础应用.md":"Dar2eeCi","src_questions_computer-base_1_计算机硬件.md":"yWllFOGD","src_questions_computer-base_2_计算机软件.md":"DD__xmtU","src_questions_computer-base_3_计算机网络.md":"BEwQL-kq","src_questions_computer-base_4_计算机编程.md":"B9LXSO_W","src_questions_computer-base_5_计算机科学.md":"DV8OyJcU","src_questions_computer-base_6_软件工程.md":"Dq38go82","src_questions_computer-base_7_计算机系统 mac.md":"VZbBUPTc","src_questions_computer-base_8_计算机系统 windows.md":"2WqTLKdf","src_questions_data-structures-algorithms_1_算法.md":"C2cLfWsV","src_questions_front-architect_1_前端架构.md":"BXhL-Puj","src_questions_front-base_1_html.md":"BkJU9mox","src_questions_front-base_2_css.md":"jTva325d","src_questions_front-base_3_javascript.md":"Dbt06Hfe","src_questions_front-base_4_typescript.md":"CFgEQYHZ","src_questions_front-component_1_ui组件库.md":"BzBvi87z","src_questions_front-component_2_业务组件库.md":"CgK5NWa1","src_questions_front-engineering_1_前端标准化.md":"C5ZOSvmA","src_questions_front-engineering_2_前端自动化.md":"HhmKP52V","src_questions_front-engineering_3_webpack.md":"C3VoK4yQ","src_questions_front-engineering_4_vite.md":"DnAlxCUt","src_questions_front-engineering_5_rollup.md":"DCp1Pxrt","src_questions_front-frame_1_react.md":"C13aIPJH","src_questions_front-frame_2_vue.md":"CKXCSiZK","src_questions_front-frame_3_next.md":"CNtIvVdT","src_questions_front-frame_4_nuxt.md":"BYOTYEZq","src_questions_front-frame_5_qiankun.md":"DC2_5_sx","src_questions_front-newest_1_前端最前沿.md":"DydqOcE1","src_questions_front-perfomance_1_前端性能优化.md":"DP1tcX-H","src_questions_front-runtime_1_浏览器.md":"Iba9Dq5f","src_questions_front-runtime_2_nodejs.md":"DKfb3aqy","src_questions_front-safety_1_前端安全.md":"CkJgBd3y","src_questions_server_1_nest.md":"C7Bpf_Nf","src_questions_server_2_mongodb.md":"sjUsLbyN","src_questions_server_3_mysql.md":"wp1a_B3f","src_questions_server_4_nginx.md":"GlyPL6yP","src_questions_server_5_docker.md":"6sFKIAhZ","src_questions_server_6_kubernets.md":"BGqfcaaX","src_questions_server_7_nacos.md":"BGmbNKcQ","src_questions_server_8_redis.md":"Bj5LGfky","src_training_training-level_w1.md":"Ct9B19gt","src_training_training-level_w2.md":"Dctj8HX-","src_training_training-level_w3.md":"DPAKgxx6","src_training_training-level_w4.md":"BhmFk_3u","src_training_training-level_w5.md":"Dxy_ldFk","src_training_training-level_w6.md":"BNvC3aYq"}
